qcvisualiser/__init__.py
qcvisualiser/datamanager.py
qcvisualiser/description.html
qcvisualiser/gain_inspector.py
qcvisualiser/inspector.py
qcvisualiser/main.py
qcvisualiser/param_inspector.py
qcvisualiser/plot_utils.py
qcvisualiser-0.0.3.dist-info/LICENSE
qcvisualiser-0.0.3.dist-info/METADATA
qcvisualiser-0.0.3.dist-info/WHEEL
qcvisualiser-0.0.3.dist-info/entry_points.txt
qcvisualiser-0.0.3.dist-info/RECORD
